logpulses/__init__.py
logpulses/db_monitor/__init__.py
logpulses/db_monitor/base.py
logpulses/db_monitor/cassandra_monitor.py
logpulses/db_monitor/initializer.py
logpulses/db_monitor/mongodb_monitor.py
logpulses/db_monitor/monitor.py
logpulses/db_monitor/mysql_monitor.py
logpulses/db_monitor/postgresql_monitor.py
logpulses/db_monitor/redis_monitor.py
logpulses/db_monitor/sqlalchemy_monitor.py
logpulses/log_storage/__init__.py
logpulses/log_storage/base.py
logpulses/log_storage/factory.py
logpulses/log_storage/local_storage.py
logpulses/log_storage/mongodb_storage.py
logpulses/log_storage/mysql_storage.py
logpulses/log_storage/postgresql_storage.py
logpulses/log_storage/sqlite_storage.py
logpulses/log_storage/utils.py
logpulses/logger/__init__.py
logpulses/logger/decorators.py
logpulses/logger/encoders.py
logpulses/logger/error_handler.py
logpulses/logger/middleware.py
logpulses/logger/request_parser.py
logpulses/logger/system_info.py
logpulses/logger/utils.py
logpulses/src/__init__.py
logpulses-1.5.0.dist-info/licenses/LICENSE
logpulses-1.5.0.dist-info/METADATA
logpulses-1.5.0.dist-info/WHEEL
logpulses-1.5.0.dist-info/top_level.txt
logpulses-1.5.0.dist-info/RECORD
