Metadata-Version: 2.4
Name: logpulses
Version: 1.5.0
Summary: Comprehensive request/response logging middleware for FastAPI with storage options and zero configuration
Home-page: https://github.com/Hari-vasan/logpulses
Author: Hariharan S
Author-email: Hariharan S <hvasan59@gmail.com>
Maintainer-email: Hariharan S <hvasan59@gmail.com>
License: MIT
Project-URL: Homepage, https://github.com/Hari-vasan/logpulses
Project-URL: Documentation, https://github.com/Hari-vasan/logpulses#readme
Project-URL: Repository, https://github.com/Hari-vasan/logpulses
Project-URL: Bug Tracker, https://github.com/Hari-vasan/logpulses/issues
Project-URL: Changelog, https://github.com/Hari-vasan/logpulses/blob/main/CHANGELOG.md
Keywords: fastapi,logging,middleware,request-logging,api-logging,monitoring,observability,database-logging,log-storage,mongodb,mysql,postgresql,sqlite,automatic-cleanup,production-logging,python api logging,fastapi middleware,request logger,fastapi logging
Classifier: Development Status :: 5 - Production/Stable
Classifier: Intended Audience :: Developers
Classifier: Topic :: Software Development :: Libraries :: Python Modules
Classifier: Topic :: Internet :: WWW/HTTP :: WSGI :: Middleware
Classifier: Topic :: System :: Logging
Classifier: Topic :: System :: Monitoring
Classifier: License :: OSI Approved :: MIT License
Classifier: Programming Language :: Python :: 3
Classifier: Programming Language :: Python :: 3.8
Classifier: Programming Language :: Python :: 3.9
Classifier: Programming Language :: Python :: 3.10
Classifier: Programming Language :: Python :: 3.11
Classifier: Programming Language :: Python :: 3.12
Classifier: Framework :: FastAPI
Classifier: Operating System :: OS Independent
Classifier: Typing :: Typed
Requires-Python: >=3.8
License-File: LICENSE
Requires-Dist: fastapi>=0.100.0
Requires-Dist: starlette>=0.27.0
Requires-Dist: psutil>=5.9.0
Requires-Dist: schedule>=1.2.0
Provides-Extra: mongodb
Requires-Dist: pymongo>=4.5.0; extra == "mongodb"
Provides-Extra: mysql
Requires-Dist: mysql-connector-python>=8.2.0; extra == "mysql"
Provides-Extra: postgresql
Requires-Dist: psycopg2-binary>=2.9.0; extra == "postgresql"
Provides-Extra: all-db
Requires-Dist: pymongo>=4.5.0; extra == "all-db"
Requires-Dist: mysql-connector-python>=8.2.0; extra == "all-db"
Requires-Dist: psycopg2-binary>=2.9.0; extra == "all-db"
Provides-Extra: dev
Requires-Dist: pytest>=7.0.0; extra == "dev"
Requires-Dist: pytest-asyncio>=0.21.0; extra == "dev"
Requires-Dist: httpx>=0.24.0; extra == "dev"
Requires-Dist: black>=23.0.0; extra == "dev"
Requires-Dist: flake8>=6.0.0; extra == "dev"
Requires-Dist: mypy>=1.0.0; extra == "dev"
Provides-Extra: full
Requires-Dist: pymongo>=4.5.0; extra == "full"
Requires-Dist: mysql-connector-python>=8.2.0; extra == "full"
Requires-Dist: psycopg2-binary>=2.9.0; extra == "full"
Requires-Dist: pytest>=7.0.0; extra == "full"
Requires-Dist: pytest-asyncio>=0.21.0; extra == "full"
Requires-Dist: httpx>=0.24.0; extra == "full"
Requires-Dist: black>=23.0.0; extra == "full"
Requires-Dist: flake8>=6.0.0; extra == "full"
Requires-Dist: mypy>=1.0.0; extra == "full"
Dynamic: author
Dynamic: home-page
Dynamic: license-file
Dynamic: requires-python
